fastapi_sqlalchemy_monitor/__init__.py
fastapi_sqlalchemy_monitor/action.py
fastapi_sqlalchemy_monitor/middleware.py
fastapi_sqlalchemy_monitor/statistics.py
fastapi_sqlalchemy_monitor-1.1.3.dist-info/METADATA
fastapi_sqlalchemy_monitor-1.1.3.dist-info/WHEEL
fastapi_sqlalchemy_monitor-1.1.3.dist-info/licenses/LICENSE
fastapi_sqlalchemy_monitor-1.1.3.dist-info/RECORD
