Metadata-Version: 2.4
Name: fastapi-sqlalchemy-monitor
Version: 1.1.3
Summary: Seamlessly track SQLAlchemy performance in FastAPI with plug-and-play monitoring middleware 🔍
Project-URL: Documentation, https://github.com/iwanbolzern/fastapi-sqlalchemy-monitor
Author: Iwan Bolzern
License-File: LICENSE
Classifier: Development Status :: 5 - Production/Stable
Classifier: Intended Audience :: Developers
Classifier: Intended Audience :: Healthcare Industry
Classifier: License :: OSI Approved :: MIT License
Classifier: Operating System :: OS Independent
Classifier: Programming Language :: Python
Classifier: Programming Language :: Python :: 3
Classifier: Programming Language :: Python :: 3.10
Classifier: Programming Language :: Python :: 3.11
Classifier: Programming Language :: Python :: 3.12
Classifier: Programming Language :: Python :: 3.13
Requires-Python: >=3.10
Requires-Dist: fastapi>=0.115.6
Requires-Dist: sqlalchemy[asyncio]>=2.0.36
